autobag/__init__.py
autobag/__main__.py
autobag/autobag.py
autobag/utils.py
autobag-0.1.0.dist-info/METADATA
autobag-0.1.0.dist-info/WHEEL
autobag-0.1.0.dist-info/entry_points.txt
autobag-0.1.0.dist-info/RECORD
