Metadata-Version: 2.3
Name: autobag
Version: 0.1.0
Summary: Add your description here
Author-email: todo <todo@todo.todo>
Requires-Python: >=3.10
Requires-Dist: autonomous-proto>=0.1.4
Requires-Dist: matplotlib>=3.10.6
Requires-Dist: pymap3d>=3.2.0
Requires-Dist: pyside6>=6.9.2
Requires-Dist: rosbags>=0.10.11
Requires-Dist: typer>=0.17.3
